toggl_track/__init__.py
toggl_track/__main__.py
toggl_track/cli.py
toggl_track/result.py
toggl_track/toggl.py
toggl_track-0.6.0.dist-info/licenses/LICENSE
toggl_track-0.6.0.dist-info/METADATA
toggl_track-0.6.0.dist-info/WHEEL
toggl_track-0.6.0.dist-info/entry_points.txt
toggl_track-0.6.0.dist-info/top_level.txt
toggl_track-0.6.0.dist-info/RECORD
