Metadata-Version: 2.4
Name: toggl-track
Version: 0.6.0
Summary: CLI tool and Python library to access Toggl Track https://toggl.com/track/
Home-page: https://github.com/zmoog/toggl-track
Author: Maurizio Branca
License: Apache License, Version 2.0
Project-URL: Issues, https://github.com/zmoog/toggl-track/issues
Project-URL: CI, https://github.com/zmoog/toggl-track/actions
Project-URL: Changelog, https://github.com/zmoog/toggl-track/releases
Requires-Python: >=3.7
License-File: LICENSE
Requires-Dist: click==8.1.8
Requires-Dist: pydantic<3
Requires-Dist: requests==2.32.3
Requires-Dist: rich==14.0.0
Provides-Extra: test
Requires-Dist: pytest==8.3.5; extra == "test"
Requires-Dist: pytest-recording==0.13.3; extra == "test"
Dynamic: author
Dynamic: description
Dynamic: description-content-type
Dynamic: home-page
Dynamic: license
Dynamic: license-file
Dynamic: project-url
Dynamic: provides-extra
Dynamic: requires-dist
Dynamic: requires-python
Dynamic: summary
